{
  "scan_time": "2026-07-09T04:27:40Z",
  "scan_time_tr": "09.07.2026 04:27",
  "count": 10,
  "results": [
    {
      "username": "bpthaber",
      "text": "Japonya Savunma Bakanı Shinjiro Koizumi:\n\n\"Ankara'daki programımızı tamamladıktan sonra İstanbul'da Türk Deniz Kuvvetleri'ne ait Deniz Müzesi'ni ziyaret ettik. \n\nAmacımız, Ertuğrul Fırkateyni ile ilgili sergiyi görmekti.\n\nBu olay, Japonya ve Türkiye arasındaki dostluk ile iyi ilişkilerden bahsederken asla unutulmaması gereken bir tarihtir.\n\nJaponya ve Türkiye tarihinin, memleketim Yokosuka ile bu şekilde bağlanması beni çok etkiledi.\n\nBize eşlik eden Türk Deniz Kuvvetleri personeline çok teşekkür ederim.\"",
      "url": "https://x.com/bpthaber/status/2074984937711698191",
      "score": 612,
      "age_h": 5.9,
      "is_breaking": false,
      "is_priority": true,
      "likes": 1709,
      "retweets": 32,
      "views": 134786,
      "velocity": 303.8,
      "eng_rate": 1.33,
      "content_fit": 1.5,
      "elazig_bonus": 1.0,
      "risk_filter": 1.0,
      "src_mult": 1.4,
      "brk_mult": 1.0
    },
    {
      "username": "pusholder",
      "text": "Emre Belözoğlu, gelmiş geçmiş en iyi 5 futbolcuyu sıraladı:\n\n1- Lionel Messi\n2- Diego Maradona\n3- Ronaldo Nazario\n4- Zinedine Zidane\n5- Paolo Maldini\n\n(Kafa Sports)",
      "url": "https://x.com/pusholder/status/2074997491972313205",
      "score": 263,
      "age_h": 5.1,
      "is_breaking": false,
      "is_priority": true,
      "likes": 944,
      "retweets": 6,
      "views": 186065,
      "velocity": 215.8,
      "eng_rate": 0.59,
      "content_fit": 1.0,
      "elazig_bonus": 1.0,
      "risk_filter": 1.0,
      "src_mult": 1.4,
      "brk_mult": 1.0
    },
    {
      "username": "pusholder",
      "text": "Lamine Yamal: \"Herkes Messi'nin kim olduğunu biliyor ama bu seviyede oynayacağını kimse beklemiyordu. Onun adına çok mutluyum. Turnuvada olmasalar da Neymar ve Cristiano adına da mutluyum. Çocukluğumuza damga vuran isimlerdi. Başlarına gelen her güzel şey beni mutlu eder. Ancak finale kalırsak, o finali kazanmak isterim.\"",
      "url": "https://x.com/pusholder/status/2074993409996009832",
      "score": 136,
      "age_h": 5.4,
      "is_breaking": false,
      "is_priority": true,
      "likes": 571,
      "retweets": 3,
      "views": 105115,
      "velocity": 112.0,
      "eng_rate": 0.57,
      "content_fit": 1.0,
      "elazig_bonus": 1.0,
      "risk_filter": 1.0,
      "src_mult": 1.4,
      "brk_mult": 1.0
    },
    {
      "username": "gusholderhaber",
      "text": "Kahramanmaraş’ta yaşanan okul saldırısında ağır yaralanan Mustafa Aslan'ın ablası: \n\n\"Bugün Mustafa Aslan’ın doğum günü. Doğum gününde tekrar ameliyat olacak. Lütfen dualarınızda Mustafa'ma da yer verin.\" https://t.co/a4af6Jp2Yk",
      "url": "https://x.com/gusholderhaber/status/2074991001458892889",
      "score": 116,
      "age_h": 5.5,
      "is_breaking": false,
      "is_priority": false,
      "likes": 537,
      "retweets": 21,
      "views": 25006,
      "velocity": 107.1,
      "eng_rate": 2.36,
      "content_fit": 1.0,
      "elazig_bonus": 1.0,
      "risk_filter": 1.0,
      "src_mult": 1.0,
      "brk_mult": 1.0
    },
    {
      "username": "bosunatiklama",
      "text": "NATO Zirvesi'nde liderlere isimlerinin işlendiği dolma kalem ile defter hediye edildi. https://t.co/OhiIMpG3dg",
      "url": "https://x.com/bosunatiklama/status/2074986817653215266",
      "score": 59,
      "age_h": 5.8,
      "is_breaking": false,
      "is_priority": false,
      "likes": 356,
      "retweets": 3,
      "views": 79788,
      "velocity": 68.8,
      "eng_rate": 0.5,
      "content_fit": 1.0,
      "elazig_bonus": 1.0,
      "risk_filter": 1.0,
      "src_mult": 1.0,
      "brk_mult": 1.0
    },
    {
      "username": "pusholder",
      "text": "Muğla’nın Bodrum ilçesinde makilik ve otluk alanda çıkan yangın, ekiplerin yaklaşık 2,5 saat süren mücadelesinin ardından söndürüldü.",
      "url": "https://x.com/pusholder/status/2075012169062592811",
      "score": 56,
      "age_h": 4.1,
      "is_breaking": false,
      "is_priority": true,
      "likes": 124,
      "retweets": 3,
      "views": 67004,
      "velocity": 32.6,
      "eng_rate": 0.2,
      "content_fit": 1.5,
      "elazig_bonus": 1.0,
      "risk_filter": 1.0,
      "src_mult": 1.4,
      "brk_mult": 1.0
    },
    {
      "username": "pusholder",
      "text": "Zonguldak’ta bir şahıs, kaza sonrası tartıştığı kadın sürücüye araçtan söktüğü dikiz aynasıyla saldırdı.\n https://t.co/yoSOFN1aJ9",
      "url": "https://x.com/pusholder/status/2075072452036878639",
      "score": 50,
      "age_h": 0.2,
      "is_breaking": false,
      "is_priority": true,
      "likes": 5,
      "retweets": 0,
      "views": 19549,
      "velocity": 44.0,
      "eng_rate": 0.06,
      "content_fit": 1.0,
      "elazig_bonus": 1.0,
      "risk_filter": 1.0,
      "src_mult": 1.4,
      "brk_mult": 1.0
    },
    {
      "username": "gusholderhaber",
      "text": "Belçika Başbakanı Bart De Wever:\n\n\"Ankara'da karşılaştığım dostça bir Türk kedisi.\" https://t.co/xBfvpYVZ7L",
      "url": "https://x.com/gusholderhaber/status/2074994400300515691",
      "score": 20,
      "age_h": 5.3,
      "is_breaking": false,
      "is_priority": false,
      "likes": 71,
      "retweets": 2,
      "views": 10896,
      "velocity": 15.1,
      "eng_rate": 0.73,
      "content_fit": 1.5,
      "elazig_bonus": 1.0,
      "risk_filter": 1.0,
      "src_mult": 1.0,
      "brk_mult": 1.0
    },
    {
      "username": "pusholder",
      "text": "Travis Kelce'nin, Taylor Swift'in yemek yapmayı öğrenmeyi reddetmesi nedeniyle hayal kırıklığı yaşadığı öne sürüldü. https://t.co/fqAB8N4ngY",
      "url": "https://x.com/pusholder/status/2074990185863852480",
      "score": 18,
      "age_h": 5.6,
      "is_breaking": false,
      "is_priority": true,
      "likes": 224,
      "retweets": 5,
      "views": 98649,
      "velocity": 52.6,
      "eng_rate": 0.3,
      "content_fit": 0.3,
      "elazig_bonus": 1.0,
      "risk_filter": 1.0,
      "src_mult": 1.4,
      "brk_mult": 1.0
    },
    {
      "username": "pusholder",
      "text": "Elon Musk: \"Yapay zeka çok hızlı ilerliyor.\"",
      "url": "https://x.com/pusholder/status/2074984875158061508",
      "score": 15,
      "age_h": 5.9,
      "is_breaking": false,
      "is_priority": true,
      "likes": 211,
      "retweets": 6,
      "views": 82273,
      "velocity": 43.7,
      "eng_rate": 0.31,
      "content_fit": 0.3,
      "elazig_bonus": 1.0,
      "risk_filter": 1.0,
      "src_mult": 1.4,
      "brk_mult": 1.0
    }
  ]
}