{
  "scan_time": "2026-06-26T19:15:58Z",
  "scan_time_tr": "26.06.2026 19:15",
  "count": 10,
  "results": [
    {
      "username": "bpthaber",
      "text": "Kadir İnanır’ın vefat haberini alan Türkan Şoray fenalaştı. https://t.co/rlZrZudpHs",
      "url": "https://x.com/bpthaber/status/2070573703784468519",
      "score": 3419,
      "age_h": 0.9,
      "is_breaking": false,
      "is_priority": true,
      "likes": 2047,
      "retweets": 24,
      "views": 133371,
      "velocity": 2461.2,
      "eng_rate": 1.6,
      "content_fit": 1.0,
      "elazig_bonus": 1.0,
      "risk_filter": 1.0,
      "src_mult": 1.4,
      "brk_mult": 1.0
    },
    {
      "username": "bpthaber",
      "text": "Kaan Ayhan'ın eşi Aylin Ayhan'ın Instagram'da beğendiği paylaşım:\n\n\"Kaptan dediğin milli takım kampında transfer görüşmesi yapmaz, çıkar golünü atar.\" https://t.co/WXTPsUpcqR",
      "url": "https://x.com/bpthaber/status/2070582559189201197",
      "score": 1683,
      "age_h": 0.3,
      "is_breaking": false,
      "is_priority": true,
      "likes": 321,
      "retweets": 5,
      "views": 32276,
      "velocity": 1285.9,
      "eng_rate": 1.12,
      "content_fit": 1.0,
      "elazig_bonus": 1.0,
      "risk_filter": 1.0,
      "src_mult": 1.4,
      "brk_mult": 1.0
    },
    {
      "username": "haskologlu",
      "text": "Türk sinemasının en önemli isimlerinden olan Kadir İnanır 77 yaşında hayatını kaybetti. https://t.co/7N1dz3nQxH",
      "url": "https://x.com/haskologlu/status/2070528276125085708",
      "score": 1652,
      "age_h": 3.9,
      "is_breaking": false,
      "is_priority": false,
      "likes": 2085,
      "retweets": 141,
      "views": 172900,
      "velocity": 673.5,
      "eng_rate": 1.51,
      "content_fit": 2.5,
      "elazig_bonus": 1.0,
      "risk_filter": 1.0,
      "src_mult": 1.0,
      "brk_mult": 1.0
    },
    {
      "username": "bpthaber",
      "text": "Ünlü oyuncu Jessica Alba, ABD - Türkiye maçında kızlarıyla birlikte görüntülendi. https://t.co/rZZk7YQdo0",
      "url": "https://x.com/bpthaber/status/2070550567777178088",
      "score": 1454,
      "age_h": 2.4,
      "is_breaking": false,
      "is_priority": true,
      "likes": 2514,
      "retweets": 31,
      "views": 269012,
      "velocity": 1128.2,
      "eng_rate": 1.01,
      "content_fit": 1.0,
      "elazig_bonus": 1.0,
      "risk_filter": 1.0,
      "src_mult": 1.4,
      "brk_mult": 1.0
    },
    {
      "username": "bosunatiklama",
      "text": "Norveç, Fransa karşısında rotasyon yaptı. \n\nİlk 11'de yer almayan isimler:\n• Haaland\n• Sörloth\n• Odegaard\n• Nyland\n• Ryerson https://t.co/fXqAEBtBq1",
      "url": "https://x.com/bosunatiklama/status/2070572117909725495",
      "score": 1319,
      "age_h": 1.0,
      "is_breaking": false,
      "is_priority": false,
      "likes": 1349,
      "retweets": 5,
      "views": 200004,
      "velocity": 1486.7,
      "eng_rate": 0.72,
      "content_fit": 1.0,
      "elazig_bonus": 1.0,
      "risk_filter": 1.0,
      "src_mult": 1.0,
      "brk_mult": 1.0
    },
    {
      "username": "pusholder",
      "text": "Fenerbahçe, yabancı sınırının kaldırılmasını teklif etti. (HT Spor) https://t.co/qC1tbQAGWq",
      "url": "https://x.com/pusholder/status/2070568662814044296",
      "score": 1271,
      "age_h": 1.2,
      "is_breaking": false,
      "is_priority": true,
      "likes": 730,
      "retweets": 7,
      "views": 89949,
      "velocity": 667.4,
      "eng_rate": 0.89,
      "content_fit": 1.5,
      "elazig_bonus": 1.0,
      "risk_filter": 1.0,
      "src_mult": 1.4,
      "brk_mult": 1.0
    },
    {
      "username": "pusholder",
      "text": "Türkan Şoray, Kadir İnanır’ın vefat haberini duyunca fenalaştı. (Birsen Altuntaş) https://t.co/hmo7olwbeT",
      "url": "https://x.com/pusholder/status/2070582249783746692",
      "score": 1035,
      "age_h": 0.3,
      "is_breaking": false,
      "is_priority": true,
      "likes": 222,
      "retweets": 9,
      "views": 52813,
      "velocity": 860.1,
      "eng_rate": 0.49,
      "content_fit": 1.0,
      "elazig_bonus": 1.0,
      "risk_filter": 1.0,
      "src_mult": 1.4,
      "brk_mult": 1.0
    },
    {
      "username": "bosunatiklama",
      "text": "Sedat Peker, 55. yaş gününü eşi ve çocuklarıyla birlikte kutladı.\n\n\"2026 senesi, Işığın Savaşçıları'nın (Devletin Çocukları'nın) yılı olacak. Doğum günümü kutlayan, benim derdimle dertlenen tüm dostlarıma ve kardeşlerime sonsuz teşekkür eder, hepsini gönülden selamlarım.\" https://t.co/bC42vyQ50f",
      "url": "https://x.com/bosunatiklama/status/2070581830714044635",
      "score": 991,
      "age_h": 0.3,
      "is_breaking": false,
      "is_priority": false,
      "likes": 190,
      "retweets": 38,
      "views": 20485,
      "velocity": 997.1,
      "eng_rate": 1.62,
      "content_fit": 1.0,
      "elazig_bonus": 1.0,
      "risk_filter": 1.0,
      "src_mult": 1.0,
      "brk_mult": 1.0
    },
    {
      "username": "bosunatiklama",
      "text": "Fenerbahçe, yabancı kuralının tamamen kaldırılması talebinde bulundu. (HT Spor) https://t.co/25uYy6eOYc",
      "url": "https://x.com/bosunatiklama/status/2070565648086831274",
      "score": 891,
      "age_h": 1.4,
      "is_breaking": false,
      "is_priority": false,
      "likes": 768,
      "retweets": 6,
      "views": 84330,
      "velocity": 640.5,
      "eng_rate": 1.07,
      "content_fit": 1.5,
      "elazig_bonus": 1.0,
      "risk_filter": 1.0,
      "src_mult": 1.0,
      "brk_mult": 1.0
    },
    {
      "username": "bpthaber",
      "text": "Otobüsün şoförü Ufuk Kıran:\n\n\"O arabayı ben durdurdum, kimsenin dahili olmadı. Caner Erkin en arkada otururken nasıl gördü onu merak ediyorum.\" https://t.co/xpLblnOu0U",
      "url": "https://x.com/bpthaber/status/2070554425739866183",
      "score": 870,
      "age_h": 2.1,
      "is_breaking": false,
      "is_priority": true,
      "likes": 1466,
      "retweets": 28,
      "views": 384495,
      "velocity": 731.7,
      "eng_rate": 0.41,
      "content_fit": 1.0,
      "elazig_bonus": 1.0,
      "risk_filter": 1.0,
      "src_mult": 1.4,
      "brk_mult": 1.0
    }
  ]
}