{
  "scan_time": "2026-06-01T23:59:21Z",
  "scan_time_tr": "01.06.2026 23:59",
  "count": 10,
  "results": [
    {
      "username": "pusholder",
      "text": "Robert Lewandowski, Fenerbahçe'ye gelmek istiyor. (Yağız Sabuncuoğlu) https://t.co/yoiSUHyl9V",
      "url": "https://x.com/pusholder/status/2061552521039032381",
      "score": 1838,
      "age_h": 3.0,
      "is_breaking": false,
      "is_priority": true,
      "likes": 2332,
      "retweets": 11,
      "views": 105770,
      "velocity": 810.5,
      "eng_rate": 2.33,
      "content_fit": 1.5,
      "elazig_bonus": 1.0,
      "risk_filter": 1.0,
      "src_mult": 1.4,
      "brk_mult": 1.0
    },
    {
      "username": "pusholder",
      "text": "Galatasaray ve Beşiktaş, TFF’nin Olağan Mali Genel Kurulu’nda yer almama kararı aldı. (HT Spor) https://t.co/yWFabXMMWz",
      "url": "https://x.com/pusholder/status/2061539548622901262",
      "score": 1114,
      "age_h": 3.9,
      "is_breaking": false,
      "is_priority": true,
      "likes": 1879,
      "retweets": 36,
      "views": 102902,
      "velocity": 513.1,
      "eng_rate": 1.95,
      "content_fit": 1.5,
      "elazig_bonus": 1.0,
      "risk_filter": 1.0,
      "src_mult": 1.4,
      "brk_mult": 1.0
    },
    {
      "username": "haskologlu",
      "text": "🔴#SONDAKİKA | CHP milletvekilleri, 12 Temmuz’da olağanüstü kurultay çağrısı yaptı. \n\n111 milletvekili, kurultayın toplanması yönündeki ortak bildiriye imza attı. https://t.co/p1z3CPkNhu",
      "url": "https://x.com/haskologlu/status/2061513060775264551",
      "score": 704,
      "age_h": 5.7,
      "is_breaking": false,
      "is_priority": false,
      "likes": 7232,
      "retweets": 503,
      "views": 722204,
      "velocity": 1496.9,
      "eng_rate": 1.17,
      "content_fit": 0.5,
      "elazig_bonus": 1.0,
      "risk_filter": 1.0,
      "src_mult": 1.0,
      "brk_mult": 1.0
    },
    {
      "username": "bpthaber",
      "text": "Hakan Safi, Robert Lewandowski ile görüşmelerinde ilerleme kaydetti.\n\nLewandowski, Fenerbahçe'ye gelmek istiyor. (Yağız Sabuncuoğlu) https://t.co/L3oHbNmcvy",
      "url": "https://x.com/bpthaber/status/2061544993576103986",
      "score": 696,
      "age_h": 3.5,
      "is_breaking": false,
      "is_priority": true,
      "likes": 1137,
      "retweets": 9,
      "views": 92154,
      "velocity": 345.7,
      "eng_rate": 1.33,
      "content_fit": 1.5,
      "elazig_bonus": 1.0,
      "risk_filter": 1.0,
      "src_mult": 1.4,
      "brk_mult": 1.0
    },
    {
      "username": "bpthaber",
      "text": "Deniz Gül, ortayı kafa ile tamamlayarak şık bir bitiriş yaptı.\n\nhttps://t.co/dWQdlCu3hh",
      "url": "https://x.com/bpthaber/status/2061520690298200111",
      "score": 630,
      "age_h": 5.2,
      "is_breaking": false,
      "is_priority": true,
      "likes": 2509,
      "retweets": 7,
      "views": 288925,
      "velocity": 496.3,
      "eng_rate": 0.88,
      "content_fit": 1.0,
      "elazig_bonus": 1.0,
      "risk_filter": 1.0,
      "src_mult": 1.4,
      "brk_mult": 1.0
    },
    {
      "username": "gusholderhaber",
      "text": "#SONDAKİKA Hakan Çalhanoğlu, Fenerbahçe ile resmi temaslara başladı. https://t.co/ZnHOQ4hwVX",
      "url": "https://x.com/gusholderhaber/status/2061575286064341326",
      "score": 599,
      "age_h": 1.5,
      "is_breaking": false,
      "is_priority": false,
      "likes": 515,
      "retweets": 10,
      "views": 22765,
      "velocity": 364.5,
      "eng_rate": 2.46,
      "content_fit": 1.5,
      "elazig_bonus": 1.0,
      "risk_filter": 1.0,
      "src_mult": 1.0,
      "brk_mult": 1.0
    },
    {
      "username": "gusholderhaber",
      "text": "Emekliye %80 zam gelebilir. https://t.co/sbfuzJg11e",
      "url": "https://x.com/gusholderhaber/status/2061525534501122541",
      "score": 535,
      "age_h": 4.8,
      "is_breaking": false,
      "is_priority": false,
      "likes": 899,
      "retweets": 23,
      "views": 127396,
      "velocity": 236.0,
      "eng_rate": 0.89,
      "content_fit": 2.5,
      "elazig_bonus": 1.0,
      "risk_filter": 1.0,
      "src_mult": 1.0,
      "brk_mult": 1.0
    },
    {
      "username": "gusholderhaber",
      "text": "#SONDAKİKA Lewandowski, Fenerbahçe’nin teklifini kabul etti. https://t.co/6kYkpS3nCT",
      "url": "https://x.com/gusholderhaber/status/2061546809713902015",
      "score": 469,
      "age_h": 3.4,
      "is_breaking": false,
      "is_priority": false,
      "likes": 1080,
      "retweets": 21,
      "views": 164201,
      "velocity": 352.1,
      "eng_rate": 0.73,
      "content_fit": 1.5,
      "elazig_bonus": 1.0,
      "risk_filter": 1.0,
      "src_mult": 1.0,
      "brk_mult": 1.0
    },
    {
      "username": "pusholder",
      "text": "CHP’de 111 milletvekili, 12 Temmuz’da olağanüstü kurultay toplanması talebiyle ortak bildiri imzaladı. (Sözcü) https://t.co/9pa5UlqgDv",
      "url": "https://x.com/pusholder/status/2061515945693049039",
      "score": 465,
      "age_h": 5.5,
      "is_breaking": false,
      "is_priority": true,
      "likes": 1187,
      "retweets": 37,
      "views": 132565,
      "velocity": 241.0,
      "eng_rate": 0.99,
      "content_fit": 1.5,
      "elazig_bonus": 1.0,
      "risk_filter": 1.0,
      "src_mult": 1.4,
      "brk_mult": 1.0
    },
    {
      "username": "gusholderhaber",
      "text": "#SONDAKİKA Küba ve Arjantinli bilim insanları, küçük hücreli akciğer kanserine AŞI üretti! \n\nAşı, bağışıklık sistemini doğrudan kanser hücrelerine harekete geçiriyor.\n\nSağlıklı dokulara zarar vermeden sadece kanser hücrelerine saldırıyor.\n\nKlinik testler, aşının hastaların yaşam süresini 2 katına çıkardığını gösterdi.",
      "url": "https://x.com/gusholderhaber/status/2061551799912349969",
      "score": 372,
      "age_h": 3.1,
      "is_breaking": false,
      "is_priority": false,
      "likes": 925,
      "retweets": 121,
      "views": 92252,
      "velocity": 389.4,
      "eng_rate": 1.31,
      "content_fit": 1.0,
      "elazig_bonus": 1.0,
      "risk_filter": 1.0,
      "src_mult": 1.0,
      "brk_mult": 1.0
    }
  ]
}