{
  "scan_time": "2026-07-17T18:32:14Z",
  "scan_time_tr": "17.07.2026 18:32",
  "count": 10,
  "results": [
    {
      "username": "bpthaber",
      "text": "Beşiktaş, Mohamed Salah ile anlaşma sağladı.\n\n— Maaş: 10.000.000 Euro.\n— Bonuslar: 2.000.000 Euro.\n— Sözleşme: 1+1 yıl.\n\n(Foot Mercato) https://t.co/Uac3DEUcfK",
      "url": "https://x.com/bpthaber/status/2078163794228826357",
      "score": 12096,
      "age_h": 1.5,
      "is_breaking": false,
      "is_priority": true,
      "likes": 7665,
      "retweets": 137,
      "views": 441528,
      "velocity": 5623.0,
      "eng_rate": 1.87,
      "content_fit": 1.5,
      "elazig_bonus": 1.0,
      "risk_filter": 1.0,
      "src_mult": 1.4,
      "brk_mult": 1.0
    },
    {
      "username": "pusholder",
      "text": "SON DAKİKA: Beşiktaş, Mohamed Salah ile yıllık 10 milyon euro maaş ve 2 milyon euro bonus içeren 1+1 yıllık sözleşme konusunda anlaşmaya vardı. (Foot Mercato)",
      "url": "https://x.com/pusholder/status/2078164583601012842",
      "score": 5272,
      "age_h": 1.4,
      "is_breaking": false,
      "is_priority": true,
      "likes": 3557,
      "retweets": 87,
      "views": 426213,
      "velocity": 2758.6,
      "eng_rate": 0.92,
      "content_fit": 1.5,
      "elazig_bonus": 1.0,
      "risk_filter": 1.0,
      "src_mult": 1.4,
      "brk_mult": 1.0
    },
    {
      "username": "gusholderhaber",
      "text": "#SONDAKİKA Beşiktaş, Mohamed Salah ile anlaştı!\n\n1+1 yıllık anlaşma sağlandı. https://t.co/MRlLKT4mkt",
      "url": "https://x.com/gusholderhaber/status/2078171708410720290",
      "score": 2329,
      "age_h": 0.9,
      "is_breaking": false,
      "is_priority": false,
      "likes": 1399,
      "retweets": 26,
      "views": 93305,
      "velocity": 1567.3,
      "eng_rate": 1.59,
      "content_fit": 1.5,
      "elazig_bonus": 1.0,
      "risk_filter": 1.0,
      "src_mult": 1.0,
      "brk_mult": 1.0
    },
    {
      "username": "bosunatiklama",
      "text": "Beşiktaş, Salah ile anlaştı. (Foot Mercato)\n\n• 1+1 yıllık sözleşme.\n• 10 milyon euro maaş + 2 milyon euro bonus. https://t.co/l5FeVIsoCv",
      "url": "https://x.com/bosunatiklama/status/2078162784760512854",
      "score": 2078,
      "age_h": 1.5,
      "is_breaking": false,
      "is_priority": false,
      "likes": 1920,
      "retweets": 45,
      "views": 121872,
      "velocity": 1374.6,
      "eng_rate": 1.73,
      "content_fit": 1.5,
      "elazig_bonus": 1.0,
      "risk_filter": 1.0,
      "src_mult": 1.0,
      "brk_mult": 1.0
    },
    {
      "username": "bpthaber",
      "text": "Aziz Yıldırım, Acun Ilıcalı’nın Fenerbahçe stadyumundaki locasını iptal etti.\n\nBaşkanlık locası yapacak. (Sercan Hamzaoğlu) https://t.co/he8yFsUIFE",
      "url": "https://x.com/bpthaber/status/2078129574257348804",
      "score": 2044,
      "age_h": 3.7,
      "is_breaking": false,
      "is_priority": true,
      "likes": 3792,
      "retweets": 33,
      "views": 361578,
      "velocity": 1046.7,
      "eng_rate": 1.08,
      "content_fit": 1.5,
      "elazig_bonus": 1.0,
      "risk_filter": 1.0,
      "src_mult": 1.4,
      "brk_mult": 1.0
    },
    {
      "username": "haskologlu",
      "text": "Milli Eğitim Bakanı Yusuf Tekin:\n\n• Ben ‘Haçlı Seferleri’ kavramını tarih müfredatından çıkardım. Sefer değil o; Haçlılar bize saldırmışlar. Bunu müfredattan çıkardık, niye itiraz ediyorsunuz?\n\n• Her gün sosyal medyada trend topic oluyorum. \n\n• Osmanlı ile Cumhuriyet’i barıştırmamız lazım. Eski Türk devletleriyle Cumhuriyet’i barıştırmamız lazım.\n\n• Çocuklarımızın Osmanlı’yı da ataları olarak bilmesi lazım. Osmanlı’ya da sahip çıkması lazım. (AA)",
      "url": "https://x.com/haskologlu/status/2078170234767446245",
      "score": 1937,
      "age_h": 1.0,
      "is_breaking": false,
      "is_priority": false,
      "likes": 1030,
      "retweets": 47,
      "views": 353951,
      "velocity": 1512.7,
      "eng_rate": 0.45,
      "content_fit": 1.5,
      "elazig_bonus": 1.0,
      "risk_filter": 1.0,
      "src_mult": 1.0,
      "brk_mult": 1.0
    },
    {
      "username": "bpthaber",
      "text": "Trabzonspor, futbolcuları Oulai’nin kaçırılmadığını açıkladı.\n\nErtuğrul Doğan: “Benim olduğum yerden kim kaçırabilir? Yurt dışına gitti.” https://t.co/icULOdg2vV",
      "url": "https://x.com/bpthaber/status/2078166137544573431",
      "score": 1762,
      "age_h": 1.3,
      "is_breaking": false,
      "is_priority": true,
      "likes": 1085,
      "retweets": 6,
      "views": 88869,
      "velocity": 878.2,
      "eng_rate": 1.3,
      "content_fit": 1.5,
      "elazig_bonus": 1.0,
      "risk_filter": 1.0,
      "src_mult": 1.4,
      "brk_mult": 1.0
    },
    {
      "username": "pusholder",
      "text": "Fenerbahçe'nin UEFA kadrosunda yer almayan isimler:\n\n-Vedat Muriqi\n-Mason Greenwood\n-Nathan Ake\n-N'Golo Kante https://t.co/e4nbME9LTd",
      "url": "https://x.com/pusholder/status/2078159007844360519",
      "score": 1419,
      "age_h": 1.8,
      "is_breaking": false,
      "is_priority": true,
      "likes": 1314,
      "retweets": 10,
      "views": 275810,
      "velocity": 785.1,
      "eng_rate": 0.51,
      "content_fit": 1.5,
      "elazig_bonus": 1.0,
      "risk_filter": 1.0,
      "src_mult": 1.4,
      "brk_mult": 1.0
    },
    {
      "username": "pusholder",
      "text": "Zinadine Zidane, Fransa'nın yeni teknik direktörü oldu. (Fabrizio Romano) https://t.co/bP0wb9bnd8",
      "url": "https://x.com/pusholder/status/2078155232085692818",
      "score": 1278,
      "age_h": 2.0,
      "is_breaking": false,
      "is_priority": true,
      "likes": 1805,
      "retweets": 12,
      "views": 114467,
      "velocity": 917.1,
      "eng_rate": 1.63,
      "content_fit": 1.0,
      "elazig_bonus": 1.0,
      "risk_filter": 1.0,
      "src_mult": 1.4,
      "brk_mult": 1.0
    },
    {
      "username": "pusholder",
      "text": "Tesla, küçük çocuklara yönelik 225 dolarlık bisikletini tanıttı. https://t.co/11aE5jV3Us",
      "url": "https://x.com/pusholder/status/2078174139920118103",
      "score": 1120,
      "age_h": 0.8,
      "is_breaking": false,
      "is_priority": true,
      "likes": 437,
      "retweets": 5,
      "views": 103187,
      "velocity": 622.7,
      "eng_rate": 0.47,
      "content_fit": 1.5,
      "elazig_bonus": 1.0,
      "risk_filter": 1.0,
      "src_mult": 1.4,
      "brk_mult": 1.0
    }
  ]
}