{
  "scan_time": "2026-07-03T09:40:39Z",
  "scan_time_tr": "03.07.2026 09:40",
  "count": 10,
  "results": [
    {
      "username": "bpthaber",
      "text": "Fenerbahçe: \"Fenerbahçe, en çok da boyun eğmediğinde Fenerbahçe'dir.\" https://t.co/Ajzi6oWCsI",
      "url": "https://x.com/bpthaber/status/2072956757530263961",
      "score": 2240,
      "age_h": 1.5,
      "is_breaking": false,
      "is_priority": true,
      "likes": 1234,
      "retweets": 24,
      "views": 43005,
      "velocity": 911.4,
      "eng_rate": 3.09,
      "content_fit": 1.5,
      "elazig_bonus": 1.0,
      "risk_filter": 1.0,
      "src_mult": 1.4,
      "brk_mult": 1.0
    },
    {
      "username": "pusholder",
      "text": "Memur ve emeklilerin zam oranları belli oldu.\n\nSSK ve Bağ-Kur emeklisi: %17,76\nMemur ve memur emeklisi: %13,52",
      "url": "https://x.com/pusholder/status/2072940641961537756",
      "score": 1703,
      "age_h": 2.5,
      "is_breaking": false,
      "is_priority": true,
      "likes": 1263,
      "retweets": 37,
      "views": 391988,
      "velocity": 576.3,
      "eng_rate": 0.37,
      "content_fit": 2.5,
      "elazig_bonus": 1.0,
      "risk_filter": 1.0,
      "src_mult": 1.4,
      "brk_mult": 1.0
    },
    {
      "username": "bpthaber",
      "text": "Emekli ve memurların alacağı zam oranı belli oldu:\n\n— Memur: %13.52\n— Emekli: %17.76 https://t.co/2yNElbcpJ9",
      "url": "https://x.com/bpthaber/status/2072940577407025632",
      "score": 1403,
      "age_h": 2.5,
      "is_breaking": false,
      "is_priority": true,
      "likes": 1064,
      "retweets": 18,
      "views": 222078,
      "velocity": 464.3,
      "eng_rate": 0.53,
      "content_fit": 2.5,
      "elazig_bonus": 1.0,
      "risk_filter": 1.0,
      "src_mult": 1.4,
      "brk_mult": 1.0
    },
    {
      "username": "pusholder",
      "text": "Kemal Sunal aramızdan ayrılalı 26 yıl oldu.\n\nhttps://t.co/ILSuZEaqyM",
      "url": "https://x.com/pusholder/status/2072963052576633073",
      "score": 1296,
      "age_h": 1.0,
      "is_breaking": false,
      "is_priority": true,
      "likes": 903,
      "retweets": 45,
      "views": 98042,
      "velocity": 998.3,
      "eng_rate": 1.06,
      "content_fit": 1.0,
      "elazig_bonus": 1.0,
      "risk_filter": 1.0,
      "src_mult": 1.4,
      "brk_mult": 1.0
    },
    {
      "username": "pusholder",
      "text": "Zam oranlarına göre en düşük maaşlar belli oldu.\n\n- En düşük emekli maaşı: 23.552 TL\n- En düşük memur emeklisi maaşı: 31.527 TL\n- En düşük memur maaşı: 70.258 TL",
      "url": "https://x.com/pusholder/status/2072947375576875468",
      "score": 1276,
      "age_h": 2.1,
      "is_breaking": false,
      "is_priority": true,
      "likes": 786,
      "retweets": 10,
      "views": 243945,
      "velocity": 431.9,
      "eng_rate": 0.37,
      "content_fit": 2.5,
      "elazig_bonus": 1.0,
      "risk_filter": 1.0,
      "src_mult": 1.4,
      "brk_mult": 1.0
    },
    {
      "username": "pusholder",
      "text": "Gram altın, son 24 saatte 300 TL değer kazanarak 6.310 TL'ye yükseldi. https://t.co/q66c3pzczt",
      "url": "https://x.com/pusholder/status/2072949714711171138",
      "score": 1195,
      "age_h": 1.9,
      "is_breaking": false,
      "is_priority": true,
      "likes": 1738,
      "retweets": 14,
      "views": 245345,
      "velocity": 958.9,
      "eng_rate": 0.75,
      "content_fit": 1.0,
      "elazig_bonus": 1.0,
      "risk_filter": 1.0,
      "src_mult": 1.4,
      "brk_mult": 1.0
    },
    {
      "username": "bosunatiklama",
      "text": "Diogo Jota ve kardeşi, bir yıl önce bugün geçirdiği trafik kazasında hayatını kaybetti. https://t.co/eG4e9VZ6ZS",
      "url": "https://x.com/bosunatiklama/status/2072926245726150870",
      "score": 1159,
      "age_h": 3.5,
      "is_breaking": false,
      "is_priority": false,
      "likes": 1350,
      "retweets": 13,
      "views": 47225,
      "velocity": 401.5,
      "eng_rate": 2.96,
      "content_fit": 2.5,
      "elazig_bonus": 1.0,
      "risk_filter": 1.0,
      "src_mult": 1.0,
      "brk_mult": 1.0
    },
    {
      "username": "gusholderhaber",
      "text": "🚨#SONDAKİKA MAAŞLARA ZAM\n\nEn düşük emekli maaşı 23 bin 552 TL\n\nEn düşük memur emekli maaşı 31 bin 527 TL\n\nEn düşük memur maaşı ise 70 bin 258 TL oldu. https://t.co/iglPuoln2J",
      "url": "https://x.com/gusholderhaber/status/2072948710707765444",
      "score": 965,
      "age_h": 2.0,
      "is_breaking": false,
      "is_priority": false,
      "likes": 2033,
      "retweets": 42,
      "views": 587382,
      "velocity": 1139.6,
      "eng_rate": 0.39,
      "content_fit": 1.0,
      "elazig_bonus": 1.0,
      "risk_filter": 1.0,
      "src_mult": 1.0,
      "brk_mult": 1.0
    },
    {
      "username": "bosunatiklama",
      "text": "Hırvatistan maçında penaltı atışı öncesi Ronaldo: \"Bismillah.\"\nhttps://t.co/ODnqc8IfP3",
      "url": "https://x.com/bosunatiklama/status/2072959085066990049",
      "score": 948,
      "age_h": 1.3,
      "is_breaking": false,
      "is_priority": false,
      "likes": 1170,
      "retweets": 20,
      "views": 104748,
      "velocity": 999.2,
      "eng_rate": 1.24,
      "content_fit": 1.0,
      "elazig_bonus": 1.0,
      "risk_filter": 1.0,
      "src_mult": 1.0,
      "brk_mult": 1.0
    },
    {
      "username": "pusholder",
      "text": "Cristiano Ronaldo: \"Penaltı atarken hiç korku hissetmedim.\" https://t.co/S45ginEZ7i",
      "url": "https://x.com/pusholder/status/2072974880711074240",
      "score": 879,
      "age_h": 0.3,
      "is_breaking": false,
      "is_priority": true,
      "likes": 167,
      "retweets": 2,
      "views": 45288,
      "velocity": 738.2,
      "eng_rate": 0.42,
      "content_fit": 1.0,
      "elazig_bonus": 1.0,
      "risk_filter": 1.0,
      "src_mult": 1.4,
      "brk_mult": 1.0
    }
  ]
}