{
  "scan_time": "2026-07-24T15:21:58Z",
  "scan_time_tr": "24.07.2026 15:21",
  "count": 10,
  "results": [
    {
      "username": "haskologlu",
      "text": "🔴#SONDAKİKA | Yargıtay Cumhuriyet Başsavcılığı Yeni Parti'yi, siyasi partiler kayıtlarına işledi. https://t.co/I18frK54SK",
      "url": "https://x.com/haskologlu/status/2080656544262189279",
      "score": 3099,
      "age_h": 1.2,
      "is_breaking": false,
      "is_priority": false,
      "likes": 3232,
      "retweets": 107,
      "views": 158571,
      "velocity": 2906.1,
      "eng_rate": 2.22,
      "content_fit": 1.0,
      "elazig_bonus": 1.0,
      "risk_filter": 1.0,
      "src_mult": 1.0,
      "brk_mult": 1.0
    },
    {
      "username": "haskologlu",
      "text": "🔴#SONDAKİKA | Özgür Özel, kurucular kurulu üyelerinin imzalarıyla Yeni Parti Genel Başkanı seçildi. https://t.co/JIO07WIUMz",
      "url": "https://x.com/haskologlu/status/2080650603856855494",
      "score": 2666,
      "age_h": 1.6,
      "is_breaking": false,
      "is_priority": false,
      "likes": 3288,
      "retweets": 116,
      "views": 109952,
      "velocity": 2237.2,
      "eng_rate": 3.26,
      "content_fit": 1.0,
      "elazig_bonus": 1.0,
      "risk_filter": 1.0,
      "src_mult": 1.0,
      "brk_mult": 1.0
    },
    {
      "username": "pusholder",
      "text": "Küçük bir çocuk, Beşiktaş forması alabilmek için su satıyor. https://t.co/VktdSE2inK",
      "url": "https://x.com/pusholder/status/2080636924000161898",
      "score": 2145,
      "age_h": 2.5,
      "is_breaking": false,
      "is_priority": true,
      "likes": 2489,
      "retweets": 53,
      "views": 233038,
      "velocity": 1086.2,
      "eng_rate": 1.17,
      "content_fit": 1.5,
      "elazig_bonus": 1.0,
      "risk_filter": 1.0,
      "src_mult": 1.4,
      "brk_mult": 1.0
    },
    {
      "username": "pusholder",
      "text": "Özgür Özel’e YENİ Parti rozetini, Adana Milletvekili Burhanettin Bulut taktı. https://t.co/GKEWpad4YN",
      "url": "https://x.com/pusholder/status/2080661982135427260",
      "score": 1202,
      "age_h": 0.8,
      "is_breaking": false,
      "is_priority": true,
      "likes": 521,
      "retweets": 8,
      "views": 78994,
      "velocity": 647.7,
      "eng_rate": 0.7,
      "content_fit": 1.5,
      "elazig_bonus": 1.0,
      "risk_filter": 1.0,
      "src_mult": 1.4,
      "brk_mult": 1.0
    },
    {
      "username": "haskologlu",
      "text": "🔴#SONDAKİKA | Kemal Kılıçdaroğlu CHP'de geriye kalan 44 Milletvekilini CHP Genel Merkezi'nde toplantıya davet etti.\n\nCHP bugün 5. parti olmuştu.",
      "url": "https://x.com/haskologlu/status/2080645269356462143",
      "score": 1015,
      "age_h": 2.0,
      "is_breaking": false,
      "is_priority": false,
      "likes": 3906,
      "retweets": 63,
      "views": 392779,
      "velocity": 2181.3,
      "eng_rate": 1.09,
      "content_fit": 0.5,
      "elazig_bonus": 1.0,
      "risk_filter": 1.0,
      "src_mult": 1.0,
      "brk_mult": 1.0
    },
    {
      "username": "haskologlu",
      "text": "Yunanistan Başbakanı Miçotakis:\n\n• Türkiye’nin ne yapacağını bilemem, ama biz tüm olası hamlelere cevaplarımızı hazırladık. \n\n• Gerçekliğe bağlı kalalım. Türkiye ile yan yana yaşamaya mahkumuz ve bu değişmeyecek. Sürekli gerilim içinde yaşamamıza  da gerek yok.\n\n• Hem Yunan hem de Türk basınında abartılı haberler yapılıyor. Haritalarla çıkıp füze menzili çizen analistler görmekten bıktık.\n\n• Yunanistan'ın her zaman öyle güçlü bir caydırıcı güce sahip olmasını istiyorum ki kimse Yunan egemenlik haklarını sorgulamayı aklından bile geçirmesin.\"",
      "url": "https://x.com/haskologlu/status/2080667338546803034",
      "score": 950,
      "age_h": 0.5,
      "is_breaking": false,
      "is_priority": false,
      "likes": 284,
      "retweets": 12,
      "views": 82203,
      "velocity": 742.1,
      "eng_rate": 0.45,
      "content_fit": 1.5,
      "elazig_bonus": 1.0,
      "risk_filter": 1.0,
      "src_mult": 1.0,
      "brk_mult": 1.0
    },
    {
      "username": "pusholder",
      "text": "Özgür Özel, oybirliğiyle Yeni Parti Genel Başkanı seçildi. https://t.co/VqLYiVsMHI",
      "url": "https://x.com/pusholder/status/2080651081109958660",
      "score": 901,
      "age_h": 1.6,
      "is_breaking": false,
      "is_priority": true,
      "likes": 999,
      "retweets": 13,
      "views": 80730,
      "velocity": 672.2,
      "eng_rate": 1.31,
      "content_fit": 1.0,
      "elazig_bonus": 1.0,
      "risk_filter": 1.0,
      "src_mult": 1.4,
      "brk_mult": 1.0
    },
    {
      "username": "pusholder",
      "text": "SON DAKİKA: En düşük emekli maaşı 23.552 TL oldu.",
      "url": "https://x.com/pusholder/status/2080657151148621882",
      "score": 900,
      "age_h": 1.2,
      "is_breaking": false,
      "is_priority": true,
      "likes": 756,
      "retweets": 16,
      "views": 114562,
      "velocity": 723.6,
      "eng_rate": 0.74,
      "content_fit": 1.0,
      "elazig_bonus": 1.0,
      "risk_filter": 1.0,
      "src_mult": 1.4,
      "brk_mult": 1.0
    },
    {
      "username": "pusholder",
      "text": "Özgür Özel Yeni PARTİ üyeleri ile birlikte yarın Anıtkabir'i ziyaret edecek. https://t.co/cAWhuBBQ0i",
      "url": "https://x.com/pusholder/status/2080666952582713695",
      "score": 888,
      "age_h": 0.5,
      "is_breaking": false,
      "is_priority": true,
      "likes": 341,
      "retweets": 6,
      "views": 47180,
      "velocity": 709.7,
      "eng_rate": 0.78,
      "content_fit": 1.0,
      "elazig_bonus": 1.0,
      "risk_filter": 1.0,
      "src_mult": 1.4,
      "brk_mult": 1.0
    },
    {
      "username": "bpthaber",
      "text": "Özgür Özel, kurucular kurulu üyeleri imzasıyla Yeni Parti Genel Başkanı seçildi. https://t.co/Pz99hPyPa5",
      "url": "https://x.com/bpthaber/status/2080651427039371519",
      "score": 775,
      "age_h": 1.5,
      "is_breaking": false,
      "is_priority": true,
      "likes": 904,
      "retweets": 7,
      "views": 142768,
      "velocity": 628.0,
      "eng_rate": 0.68,
      "content_fit": 1.0,
      "elazig_bonus": 1.0,
      "risk_filter": 1.0,
      "src_mult": 1.4,
      "brk_mult": 1.0
    }
  ]
}