{
  "scan_time": "2026-06-25T11:12:39Z",
  "scan_time_tr": "25.06.2026 11:12",
  "count": 10,
  "results": [
    {
      "username": "bpthaber",
      "text": "Mersin'de 5 yaşındaki otizmli çocuğa şiddet uygulayan öğretmen tutuklandı.\n\n— Şiddet gördüğü okulun önünden geçen çocuk, binayı tanıyınca ağlarken görüntülendi. https://t.co/7xjlUvOdLp",
      "url": "https://x.com/bpthaber/status/2070083185560412650",
      "score": 1514,
      "age_h": 1.3,
      "is_breaking": false,
      "is_priority": true,
      "likes": 535,
      "retweets": 18,
      "views": 94154,
      "velocity": 491.0,
      "eng_rate": 0.68,
      "content_fit": 2.5,
      "elazig_bonus": 1.0,
      "risk_filter": 1.0,
      "src_mult": 1.4,
      "brk_mult": 1.0
    },
    {
      "username": "bpthaber",
      "text": "ÖSYM, YKS ve benzeri sınavlarda uygulanan 15 dakika önce kapı kapatma kuralını değiştirmeyecek.\n\nÖSYM: \"Esnetilirse sınav güvenliği riske girer, kaosa yol açabilir.\" https://t.co/mdvyUlE4oU",
      "url": "https://x.com/bpthaber/status/2070072063511953549",
      "score": 1338,
      "age_h": 2.0,
      "is_breaking": false,
      "is_priority": true,
      "likes": 1913,
      "retweets": 7,
      "views": 142182,
      "velocity": 985.7,
      "eng_rate": 1.41,
      "content_fit": 1.0,
      "elazig_bonus": 1.0,
      "risk_filter": 1.0,
      "src_mult": 1.4,
      "brk_mult": 1.0
    },
    {
      "username": "bosunatiklama",
      "text": "İbrahim Hacıosmanoğlu, Ahmet Çakar hakkında suç duyurusunda bulunacak.\n\nAhmet Çakar: Bizim çocuklar, acaba başka çocuklar olma yolunda ilerliyorlar mı?\n\nHacıosmanoğlu: 'Bizim çocuklar değil, onun bunun çocukları' dedi. Bu çocukların aileleri var.\n\nAhmet Çakar: Artık okuduğunu anlama zamanın geldi. Lütfen eğitim al, ilk eğitimini ben vereyim:\n\nİbrahim, topu tut. Tut İbrahim, tut. Topu tut İbrahim. Türkçemizde bu, ilköğretim seviyesinde verilen ilk eğitimlerimizdendir.",
      "url": "https://x.com/bosunatiklama/status/2070085739182772483",
      "score": 1159,
      "age_h": 1.1,
      "is_breaking": false,
      "is_priority": false,
      "likes": 1263,
      "retweets": 22,
      "views": 102110,
      "velocity": 1206.4,
      "eng_rate": 1.34,
      "content_fit": 1.0,
      "elazig_bonus": 1.0,
      "risk_filter": 1.0,
      "src_mult": 1.0,
      "brk_mult": 1.0
    },
    {
      "username": "haskologlu",
      "text": "🔴#SONDAKİKA | Malatya Kürecik Üssü'ne Almanya'ya ait Patriot Hava Savunma Sistemi konuşlandırıldı.",
      "url": "https://x.com/haskologlu/status/2070072621803127163",
      "score": 1136,
      "age_h": 2.0,
      "is_breaking": false,
      "is_priority": false,
      "likes": 2306,
      "retweets": 66,
      "views": 286852,
      "velocity": 1254.7,
      "eng_rate": 0.88,
      "content_fit": 1.0,
      "elazig_bonus": 1.0,
      "risk_filter": 1.0,
      "src_mult": 1.0,
      "brk_mult": 1.0
    },
    {
      "username": "pusholder",
      "text": "Mersin'de otizm tanısı bulunan 5 yaşındaki bir çocuğa şiddet uygulayan öğretmen tutuklandı. https://t.co/f3MgHGJEMc",
      "url": "https://x.com/pusholder/status/2070097702075920822",
      "score": 1104,
      "age_h": 0.3,
      "is_breaking": false,
      "is_priority": true,
      "likes": 79,
      "retweets": 7,
      "views": 54674,
      "velocity": 380.9,
      "eng_rate": 0.24,
      "content_fit": 2.5,
      "elazig_bonus": 1.0,
      "risk_filter": 1.0,
      "src_mult": 1.4,
      "brk_mult": 1.0
    },
    {
      "username": "bosunatiklama",
      "text": "ÖSYM, kapıların sınavdan 15 dakika önce kapatılması kuralının değişmeyeceğini açıkladı. https://t.co/2lkRWCG89o",
      "url": "https://x.com/bosunatiklama/status/2070072956449923538",
      "score": 1049,
      "age_h": 2.0,
      "is_breaking": false,
      "is_priority": false,
      "likes": 2097,
      "retweets": 12,
      "views": 200021,
      "velocity": 1123.8,
      "eng_rate": 1.11,
      "content_fit": 1.0,
      "elazig_bonus": 1.0,
      "risk_filter": 1.0,
      "src_mult": 1.0,
      "brk_mult": 1.0
    },
    {
      "username": "bpthaber",
      "text": "Lucas Torreira: \"Galatasaray-Fenerbahçe, en ateşli ve aynı zamanda Güney Amerika'dakilere en çok benzeyen derbi.\n\nRakip taraftarların bana küfretmesinden keyif alıyorum. Çok hoşuma gidiyor.\" https://t.co/ZVW44ibjlk",
      "url": "https://x.com/bpthaber/status/2070069609135308856",
      "score": 1020,
      "age_h": 2.2,
      "is_breaking": false,
      "is_priority": true,
      "likes": 985,
      "retweets": 6,
      "views": 98080,
      "velocity": 517.1,
      "eng_rate": 1.16,
      "content_fit": 1.5,
      "elazig_bonus": 1.0,
      "risk_filter": 1.0,
      "src_mult": 1.4,
      "brk_mult": 1.0
    },
    {
      "username": "pusholder",
      "text": "25 Haziran | Aşure Günü. https://t.co/NDvI3qIOpP",
      "url": "https://x.com/pusholder/status/2070054386605158417",
      "score": 850,
      "age_h": 3.2,
      "is_breaking": false,
      "is_priority": true,
      "likes": 1741,
      "retweets": 30,
      "views": 104347,
      "velocity": 595.2,
      "eng_rate": 1.83,
      "content_fit": 1.0,
      "elazig_bonus": 1.0,
      "risk_filter": 1.0,
      "src_mult": 1.4,
      "brk_mult": 1.0
    },
    {
      "username": "bpthaber",
      "text": "Manifest'in menajeri Tolga Akış: \"Manifest şu an karlı bir proje değil. Sadece tek bir klip setinin maliyeti bile iki haneli milyon rakamlara ulaşıyor.\"\n\nArkalarında güvenlik ekibinden psikolog takımına kadar 143 kişi çalışıyor.\" https://t.co/3uxQQaVP3H",
      "url": "https://x.com/bpthaber/status/2070048812278636937",
      "score": 797,
      "age_h": 3.6,
      "is_breaking": false,
      "is_priority": true,
      "likes": 2161,
      "retweets": 10,
      "views": 519674,
      "velocity": 666.1,
      "eng_rate": 0.46,
      "content_fit": 1.0,
      "elazig_bonus": 1.0,
      "risk_filter": 1.0,
      "src_mult": 1.4,
      "brk_mult": 1.0
    },
    {
      "username": "bpthaber",
      "text": "Lucas Torreira öğrendiği Türkçe küfrü söylüyor: https://t.co/2f3DpMZbjH",
      "url": "https://x.com/bpthaber/status/2070084940557881479",
      "score": 758,
      "age_h": 1.2,
      "is_breaking": false,
      "is_priority": true,
      "likes": 676,
      "retweets": 9,
      "views": 117287,
      "velocity": 618.6,
      "eng_rate": 0.62,
      "content_fit": 1.0,
      "elazig_bonus": 1.0,
      "risk_filter": 1.0,
      "src_mult": 1.4,
      "brk_mult": 1.0
    }
  ]
}