{
  "scan_time": "2026-06-19T20:52:52Z",
  "scan_time_tr": "19.06.2026 20:52",
  "count": 10,
  "results": [
    {
      "username": "pusholder",
      "text": "Fenerbahçe Beko, Basketbol Süper Ligi’nde üst üste üçüncü kez şampiyonluğa ulaştı. https://t.co/IhMjihrsdy",
      "url": "https://x.com/pusholder/status/2068047441207742654",
      "score": 6276,
      "age_h": 1.8,
      "is_breaking": false,
      "is_priority": true,
      "likes": 3637,
      "retweets": 76,
      "views": 70474,
      "velocity": 2134.7,
      "eng_rate": 5.43,
      "content_fit": 1.5,
      "elazig_bonus": 1.0,
      "risk_filter": 1.0,
      "src_mult": 1.4,
      "brk_mult": 1.0
    },
    {
      "username": "haskologlu",
      "text": "🔴#SONDAKİKA Teğmenlerin kılıçlı yemini sonrası yürütülen soruşturmada ihraç edilen Tabur Komutanı Halit Türkoğlu hakkında yürütülen işlem mahkemece İPTAL EDİLDİ. \n\nKararla birlikte ihraç edilen 3 komutan yeniden görevine dönüyor. https://t.co/ujbhY4NPaB",
      "url": "https://x.com/haskologlu/status/2067997715695571153",
      "score": 5840,
      "age_h": 5.1,
      "is_breaking": false,
      "is_priority": false,
      "likes": 18641,
      "retweets": 1175,
      "views": 414621,
      "velocity": 4171.5,
      "eng_rate": 5.12,
      "content_fit": 1.0,
      "elazig_bonus": 1.0,
      "risk_filter": 1.0,
      "src_mult": 1.0,
      "brk_mult": 1.0
    },
    {
      "username": "haskologlu",
      "text": "🔴#SONDAKİKA | ABD Başkanı Donald Trump, Türkiye’ye geleceğini açıkladı.",
      "url": "https://x.com/haskologlu/status/2068061293740019739",
      "score": 2348,
      "age_h": 0.9,
      "is_breaking": false,
      "is_priority": false,
      "likes": 1901,
      "retweets": 48,
      "views": 177139,
      "velocity": 2479.2,
      "eng_rate": 1.23,
      "content_fit": 1.0,
      "elazig_bonus": 1.0,
      "risk_filter": 1.0,
      "src_mult": 1.0,
      "brk_mult": 1.0
    },
    {
      "username": "pusholder",
      "text": "SON DAKİKA: Kadıköy–Sabiha Gökçen Havalimanı metrosu Bostancı’da raydan çıktı.",
      "url": "https://x.com/pusholder/status/2068018801107517938",
      "score": 2229,
      "age_h": 3.7,
      "is_breaking": false,
      "is_priority": true,
      "likes": 6459,
      "retweets": 80,
      "views": 1666825,
      "velocity": 1873.3,
      "eng_rate": 0.41,
      "content_fit": 1.0,
      "elazig_bonus": 1.0,
      "risk_filter": 1.0,
      "src_mult": 1.4,
      "brk_mult": 1.0
    },
    {
      "username": "bpthaber",
      "text": "Fenerbahçe Beko kupasını kaldırdı. https://t.co/kq22Gc5Fbb",
      "url": "https://x.com/bpthaber/status/2068059704568254718",
      "score": 2072,
      "age_h": 1.0,
      "is_breaking": false,
      "is_priority": true,
      "likes": 782,
      "retweets": 14,
      "views": 27771,
      "velocity": 850.8,
      "eng_rate": 3.0,
      "content_fit": 1.5,
      "elazig_bonus": 1.0,
      "risk_filter": 1.0,
      "src_mult": 1.4,
      "brk_mult": 1.0
    },
    {
      "username": "bosunatiklama",
      "text": "Fenerbahçe Beko, Türkiye Basketbol Ligi'nde üst üste 3. kez şampiyon oldu.🏆 https://t.co/pV6SYCbBN2",
      "url": "https://x.com/bosunatiklama/status/2068047006891675887",
      "score": 2050,
      "age_h": 1.8,
      "is_breaking": false,
      "is_priority": false,
      "likes": 1790,
      "retweets": 42,
      "views": 47432,
      "velocity": 1060.6,
      "eng_rate": 4.07,
      "content_fit": 1.5,
      "elazig_bonus": 1.0,
      "risk_filter": 1.0,
      "src_mult": 1.0,
      "brk_mult": 1.0
    },
    {
      "username": "bosunatiklama",
      "text": "Tony Soprano karakteriyle tanınan James Gandolfini, 13 yıl önce bugün hayatını kaybetti. https://t.co/WilSEwz5gb",
      "url": "https://x.com/bosunatiklama/status/2068011995429818399",
      "score": 1826,
      "age_h": 4.1,
      "is_breaking": false,
      "is_priority": false,
      "likes": 3076,
      "retweets": 47,
      "views": 300214,
      "velocity": 785.5,
      "eng_rate": 1.08,
      "content_fit": 2.5,
      "elazig_bonus": 1.0,
      "risk_filter": 1.0,
      "src_mult": 1.0,
      "brk_mult": 1.0
    },
    {
      "username": "bpthaber",
      "text": "Tony Soprano karakteriyle tanınan James Gandolfini, 13 yıl önce bugün hayatını kaybetti. https://t.co/ZUBTwUUF0u",
      "url": "https://x.com/bpthaber/status/2068040073870803026",
      "score": 1696,
      "age_h": 2.3,
      "is_breaking": false,
      "is_priority": true,
      "likes": 995,
      "retweets": 25,
      "views": 58164,
      "velocity": 473.9,
      "eng_rate": 1.86,
      "content_fit": 2.5,
      "elazig_bonus": 1.0,
      "risk_filter": 1.0,
      "src_mult": 1.4,
      "brk_mult": 1.0
    },
    {
      "username": "bpthaber",
      "text": "Cumhurbaşkanı Erdoğan, Türkiye Sigorta Basketbol Süper Ligi Şampiyonu olan Fenerbahçe Beko'yu tebrik etti. https://t.co/QW9Y5kMVmt",
      "url": "https://x.com/bpthaber/status/2068069553750331664",
      "score": 1561,
      "age_h": 0.3,
      "is_breaking": false,
      "is_priority": true,
      "likes": 230,
      "retweets": 3,
      "views": 15775,
      "velocity": 753.2,
      "eng_rate": 1.56,
      "content_fit": 1.5,
      "elazig_bonus": 1.0,
      "risk_filter": 1.0,
      "src_mult": 1.4,
      "brk_mult": 1.0
    },
    {
      "username": "bpthaber",
      "text": "\"Friends\", \"Cheers\" ve \"The Big Bang Theory\" dizilerinin yönetmenliğini yapan James Burrows, 85 yaşında hayatını kaybetti. https://t.co/78RwF0NjDd",
      "url": "https://x.com/bpthaber/status/2068071975474393258",
      "score": 1461,
      "age_h": 0.2,
      "is_breaking": false,
      "is_priority": true,
      "likes": 96,
      "retweets": 0,
      "views": 7331,
      "velocity": 428.0,
      "eng_rate": 1.46,
      "content_fit": 2.5,
      "elazig_bonus": 1.0,
      "risk_filter": 1.0,
      "src_mult": 1.4,
      "brk_mult": 1.0
    }
  ]
}